{
  "id": "0f18d106-82df-42b0-8f4b-b1b235dcd88b",
  "code": "class OptimizedSolver:\n    def __init__(self):\n        self.iteration = 18\n        self.island = 1\n        self.score = 0.7464\n        self.params = {\"alpha\": 0.566, \"beta\": 0.658, \"gamma\": 0.435}\n    \n    def solve(self, problem):\n        return problem * self.params['alpha'] + self.score",
  "language": "python",
  "metrics": {
    "combined_score": 0.7463754978731251,
    "accuracy": 0.7051313112970202,
    "efficiency": 0.781752149402283,
    "complexity": 0.6942416329439758,
    "robustness": 0.6928036689044721
  },
  "iteration_found": 18,
  "parent_id": null,
  "metadata": {
    "island": 1,
    "created_at": "2024-01-19T18:00:00Z"
  }
}